[
    {
        "title": "12-PBG-25-098, Tr\u00e4gerschaft f\u00fcr die Offene Ganztagsschule der Grundschule Thesdorf in Pinneberg\nOffenes Verfahren",
        "link": " "
    },
    {
        "title": "12-PBG-25-099; GS R\u00fcbekamp, Offener Ganztag\nOffenes Verfahren",
        "link": " "
    },
    {
        "title": "13/25 Unterhaltsreinigung in drei Grundschulen\n\u00d6ffentliche Ausschreibung",
        "link": " "
    },
    {
        "title": "13853 - Kreisgymnasium Halle (Westf.) - Herstellung, Lieferung und Montage eines Spielger\u00e4tes\n\u00d6ffentliche Ausschreibung",
        "link": " "
    },
    {
        "title": "14060 Gaslieferung 2026 - 2029 f\u00fcr St\u00e4dt. Liegenschaften der Stadt Schlo\u00df Holte-Stukenbrock\nOffenes Verfahren",
        "link": " "
    },
    {
        "title": "14075 IT-Technik Kreisleitstelle G\u00fctersloh\nOffenes Verfahren",
        "link": " "
    },
    {
        "title": "14115 Beschaffung von 8 Utility Task Vehicle\nOffenes Verfahren",
        "link": " "
    },
    {
        "title": "14150 Beschaffung eines Traktors mit Frontlader\n\u00d6ffentliche Ausschreibung",
        "link": " "
    },
    {
        "title": "14181 - Kanalsanierung in geschlossener Bauweise im Sanierungsgebiet OST 2\n\u00d6ffentliche Ausschreibung",
        "link": " "
    },
    {
        "title": "14194 Umgestaltung des Casumer Bachs im Bereich Halstenbeck in Versmold\n\u00d6ffentliche Ausschreibung",
        "link": " "
    },
    {
        "title": "14201 Verbreiterung des Geh-/Radweges und Ausbau der K23 (Casumer Stra\u00dfe) in Versmold\n\u00d6ffentliche Ausschreibung",
        "link": " "
    },
    {
        "title": "14216 - Beschaffung eines Frontauslegers f\u00fcr den st\u00e4dtischen Bauhof\n\u00d6ffentliche Ausschreibung",
        "link": " "
    },
    {
        "title": "14217 - Verkehrssicherung Lange Stra\u00dfe\n\u00d6ffentliche Ausschreibung",
        "link": " "
    },
    {
        "title": "14223 - Beschaffung eines Tanksystems mit Hei\u00dfwasseranlage f\u00fcr den st\u00e4dtischen Bauhof\n\u00d6ffentliche Ausschreibung",
        "link": " "
    },
    {
        "title": "14224: Ersatzneubau Br\u00fcckenbauwerk 0000 105 \u00fcber der K23 (Casumer Stra\u00dfe) in Versmold\n\u00d6ffentliche Ausschreibung",
        "link": " "
    },
    {
        "title": "14236 Unterhalts- und Glasreinigung an st\u00e4dt. Geb\u00e4uden der Stadt Schlo\u00df Holte-Stukenbrock\nOffenes Verfahren",
        "link": " "
    },
    {
        "title": "14262 - Splittzug 2025\n\u00d6ffentliche Ausschreibung",
        "link": " "
    },
    {
        "title": "14280 Erdung und Blitzschutz f\u00fcr den Neubau der Feuerwehr Bockhorst/Versmold\n\u00d6ffentliche Ausschreibung",
        "link": " "
    },
    {
        "title": "14281 Elektroinstallation f\u00fcr den Neubau der Feuerwehr Bockhorst/Versmold\n\u00d6ffentliche Ausschreibung",
        "link": " "
    },
    {
        "title": "14-AR-25-025; Umgestaltung \u00f6ffentlicher Spielplatz in Bilsen, Lieferung und Aufbau von Spielger\u00e4ten\n\u00d6ffentliche Ausschreibung",
        "link": " "
    },
    {
        "title": "Anbau und Erweiterung Grundschule Gunzenbach \u2013 Fachplanung Technische Ausr\u00fcstung ELT\nOffenes Verfahren",
        "link": " "
    },
    {
        "title": "Anbau und Erweiterung Grundschule Gunzenbach \u2013 Fachplanung Technische Ausr\u00fcstung HLS\nOffenes Verfahren",
        "link": " "
    },
    {
        "title": "Anbau und Erweiterung Grundschule Gunzenbach \u2013 Fachplanung Tragwerksplanung\nOffenes Verfahren",
        "link": " "
    },
    {
        "title": "Anfertigung von 18 Videotrailern f\u00fcr die Schauspielproduktionen der Spielzeit 2025/26.\n\u00d6ffentliche Ausschreibung",
        "link": " "
    },
    {
        "title": "Anfertigung von 3 Videotrailer f\u00fcr Opernproduktionen (2) Staatstheater N\u00fcrnberg\n\u00d6ffentliche Ausschreibung",
        "link": " "
    }
]